osuExchange/__init__.py
osuExchange/api.py
osuExchange/auth.py
osuExchange/client.py
osuExchange/endpoints.py
osuExchange/enums.py
osuExchange/structures.py
osuExchange/typing.py
osuExchange/unauth_endpoints.py
osuExchange-0.0.9.dist-info/METADATA
osuExchange-0.0.9.dist-info/WHEEL
osuExchange-0.0.9.dist-info/top_level.txt
osuExchange-0.0.9.dist-info/RECORD
