Metadata-Version: 2.1
Name: osuExchange
Version: 0.0.9
Summary: A simple osu!APIv2 wrapper for Python
Author: trustytrojan, alittlerocket
Project-URL: Homepage, https://github.com/alittlerocket/osuExchange
Requires-Dist: requests
